ipyslurm/__init__.py
ipyslurm/magic.py
ipyslurm/sftp.py
ipyslurm/slurm.py
ipyslurm/ssh.py
ipyslurm/util.py
ipyslurm/version.py
ipyslurm-2.3.0.dist-info/LICENSE.md
ipyslurm-2.3.0.dist-info/METADATA
ipyslurm-2.3.0.dist-info/WHEEL
ipyslurm-2.3.0.dist-info/top_level.txt
ipyslurm-2.3.0.dist-info/RECORD
