Metadata-Version: 2.2
Name: ipyslurm
Version: 2.3.0
Summary: Python interface to Slurm Workload Manager.
Author: Ali Uneri
Project-URL: Homepage, https://auneri.github.io/ipyslurm
Project-URL: Repository, https://github.com/auneri/ipyslurm
Classifier: Framework :: IPython
Classifier: License :: OSI Approved :: MIT License
Classifier: Operating System :: OS Independent
Classifier: Programming Language :: Python :: 3
Requires-Python: >=3.8
License-File: LICENSE.md
Requires-Dist: ipython>=7
Requires-Dist: paramiko>=2.5
Requires-Dist: tqdm>=4
Provides-Extra: flake8
Requires-Dist: flake8; extra == "flake8"
Requires-Dist: flake8-bugbear; extra == "flake8"
Requires-Dist: flake8-builtins; extra == "flake8"
Requires-Dist: flake8-comprehensions; extra == "flake8"
Requires-Dist: flake8-docstrings; extra == "flake8"
Requires-Dist: flake8-import-order; extra == "flake8"
Requires-Dist: flake8-mutable; extra == "flake8"
Requires-Dist: flake8-pyproject; extra == "flake8"
Requires-Dist: flake8-quotes; extra == "flake8"
Requires-Dist: flake8-use-fstring; extra == "flake8"
Requires-Dist: flake8-use-pathlib; extra == "flake8"
Requires-Dist: pep8-naming; extra == "flake8"
Provides-Extra: interactive
Requires-Dist: ipywidgets>=7; extra == "interactive"
